{
  "last_updated": "2026-05-17T04:11:05.899707+00:00",
  "total_students": 1358,
  "schools": [
    {
      "name": "Cygnus World School",
      "code": "cygnus",
      "count": 369
    },
    {
      "name": "Delhi Public School Harni (DPS Harni)",
      "code": "dpshar",
      "count": 989
    }
  ],
  "school_stats": {
    "cygnus": {
      "total_students": 369,
      "class_counts": {
        "7": 119,
        "8": 134,
        "9": 116
      },
      "section_counts": {
        "7-A": 28,
        "7-B": 31,
        "7-C": 30,
        "7-D": 30,
        "8-A": 34,
        "8-B": 33,
        "8-C": 34,
        "8-D": 33,
        "9-A": 28,
        "9-B": 30,
        "9-C": 29,
        "9-D": 29
      },
      "gender_counts": {
        "male": 112,
        "female": 69,
        "prefer_not_to_say": 188
      },
      "students_with_phone": 254,
      "students_with_email": 0,
      "gems_total": 35950,
      "gems_avg": 97.4,
      "gems_max": 1013,
      "coins_total": 1604820,
      "coins_avg": 4349.1,
      "coins_max": 37865,
      "zero_gems_count": 21,
      "total_teachers_found": 0,
      "total_teachers_cracked": 0,
      "total_teachers_locked": 0
    },
    "dpshar": {
      "total_students": 989,
      "class_counts": {
        "10": 186,
        "5": 2,
        "6": 22,
        "7": 288,
        "8": 274,
        "9": 217
      },
      "section_counts": {
        "10-A": 32,
        "10-B": 34,
        "10-C": 39,
        "10-D": 32,
        "10-E": 18,
        "10-F": 20,
        "10-G": 7,
        "10-H": 4,
        "5-E": 1,
        "5-H": 1,
        "6-A": 2,
        "6-B": 2,
        "6-C": 5,
        "6-D": 2,
        "6-F": 5,
        "6-G": 1,
        "6-H": 2,
        "6-I": 3,
        "7-A": 35,
        "7-B": 38,
        "7-C": 34,
        "7-D": 35,
        "7-E": 42,
        "7-F": 34,
        "7-G": 36,
        "7-H": 34,
        "8-A": 28,
        "8-B": 35,
        "8-C": 42,
        "8-D": 33,
        "8-E": 32,
        "8-F": 34,
        "8-G": 33,
        "8-H": 37,
        "9-A": 38,
        "9-B": 35,
        "9-C": 28,
        "9-D": 17,
        "9-E": 21,
        "9-F": 33,
        "9-G": 30,
        "9-H": 15
      },
      "gender_counts": {
        "female": 208,
        "prefer_not_to_say": 518,
        "male": 263
      },
      "students_with_phone": 989,
      "students_with_email": 905,
      "gems_total": 117140,
      "gems_avg": 118.4,
      "gems_max": 859,
      "coins_total": 3509105,
      "coins_avg": 3548.1,
      "coins_max": 33060,
      "zero_gems_count": 13,
      "total_teachers_found": 5,
      "total_teachers_cracked": 4,
      "total_teachers_locked": 1
    }
  },
  "total_teachers_found": 5,
  "total_teachers_cracked": 4,
  "total_teachers_in_list": 52,
  "gems_total": 153090,
  "gems_avg": 112.7,
  "gems_max": 1013,
  "coins_total": 5113925,
  "coins_avg": 3765.8,
  "coins_max": 37865,
  "zero_gems_count": 34,
  "students_with_phone": 1243,
  "students_with_email": 905,
  "total_sections": 54
}